{
  "arms": [
    {
      "label": "Arm A",
      "coordinates": [
        {
          "t": 0.0,
          "s": 1.0
        },
        {
          "t": 1.3315,
          "s": 0.993789
        },
        {
          "t": 1.5763,
          "s": 0.987539
        },
        {
          "t": 2.0049,
          "s": 0.981288
        },
        {
          "t": 2.1331,
          "s": 0.974998
        },
        {
          "t": 2.2468,
          "s": 0.968667
        },
        {
          "t": 2.5831,
          "s": 0.962336
        },
        {
          "t": 2.5856,
          "s": 0.956005
        },
        {
          "t": 2.635,
          "s": 0.949673
        },
        {
          "t": 2.6884,
          "s": 0.943342
        },
        {
          "t": 2.7145,
          "s": 0.937011
        },
        {
          "t": 2.7572,
          "s": 0.93068
        },
        {
          "t": 2.9848,
          "s": 0.924349
        },
        {
          "t": 3.0126,
          "s": 0.918018
        },
        {
          "t": 3.4268,
          "s": 0.911686
        },
        {
          "t": 3.5232,
          "s": 0.905355
        },
        {
          "t": 3.5724,
          "s": 0.89898
        },
        {
          "t": 3.6142,
          "s": 0.892604
        },
        {
          "t": 3.687,
          "s": 0.886228
        },
        {
          "t": 3.7751,
          "s": 0.879852
        },
        {
          "t": 3.8072,
          "s": 0.873477
        },
        {
          "t": 3.9705,
          "s": 0.867101
        },
        {
          "t": 4.1377,
          "s": 0.860725
        },
        {
          "t": 4.16,
          "s": 0.854349
        },
        {
          "t": 4.1699,
          "s": 0.847974
        },
        {
          "t": 4.2089,
          "s": 0.841598
        },
        {
          "t": 4.3253,
          "s": 0.835222
        },
        {
          "t": 4.4256,
          "s": 0.828846
        },
        {
          "t": 4.4338,
          "s": 0.822471
        },
        {
          "t": 4.4737,
          "s": 0.816045
        },
        {
          "t": 4.5963,
          "s": 0.80962
        },
        {
          "t": 4.8246,
          "s": 0.803194
        },
        {
          "t": 4.8792,
          "s": 0.796768
        },
        {
          "t": 5.0492,
          "s": 0.790343
        },
        {
          "t": 5.1163,
          "s": 0.783917
        },
        {
          "t": 5.5233,
          "s": 0.777439
        },
        {
          "t": 5.5665,
          "s": 0.77096
        },
        {
          "t": 5.5902,
          "s": 0.764481
        },
        {
          "t": 5.6088,
          "s": 0.758003
        },
        {
          "t": 5.6175,
          "s": 0.751524
        },
        {
          "t": 5.6763,
          "s": 0.745045
        },
        {
          "t": 5.7044,
          "s": 0.738567
        },
        {
          "t": 5.7873,
          "s": 0.732088
        },
        {
          "t": 5.8436,
          "s": 0.725609
        },
        {
          "t": 5.8947,
          "s": 0.719131
        },
        {
          "t": 5.9537,
          "s": 0.712652
        },
        {
          "t": 5.9637,
          "s": 0.706173
        },
        {
          "t": 6.0381,
          "s": 0.699695
        },
        {
          "t": 6.0665,
          "s": 0.693216
        },
        {
          "t": 6.184,
          "s": 0.686738
        },
        {
          "t": 6.2722,
          "s": 0.680259
        },
        {
          "t": 6.2875,
          "s": 0.67378
        },
        {
          "t": 6.3554,
          "s": 0.667302
        },
        {
          "t": 6.3845,
          "s": 0.660823
        },
        {
          "t": 6.5361,
          "s": 0.654344
        },
        {
          "t": 6.5919,
          "s": 0.647866
        },
        {
          "t": 6.5991,
          "s": 0.641387
        },
        {
          "t": 6.6158,
          "s": 0.634908
        },
        {
          "t": 6.7004,
          "s": 0.62843
        },
        {
          "t": 6.7159,
          "s": 0.621951
        },
        {
          "t": 6.8405,
          "s": 0.615472
        },
        {
          "t": 6.8483,
          "s": 0.608994
        },
        {
          "t": 6.8778,
          "s": 0.602515
        },
        {
          "t": 7.1131,
          "s": 0.596036
        },
        {
          "t": 7.1594,
          "s": 0.589558
        },
        {
          "t": 7.2006,
          "s": 0.583079
        },
        {
          "t": 7.2108,
          "s": 0.5766
        },
        {
          "t": 7.2683,
          "s": 0.570122
        },
        {
          "t": 7.2855,
          "s": 0.563643
        },
        {
          "t": 7.3651,
          "s": 0.557164
        },
        {
          "t": 7.6296,
          "s": 0.550686
        },
        {
          "t": 7.8319,
          "s": 0.54413
        },
        {
          "t": 7.856,
          "s": 0.537574
        },
        {
          "t": 8.1173,
          "s": 0.531018
        },
        {
          "t": 8.2546,
          "s": 0.524463
        },
        {
          "t": 8.3446,
          "s": 0.517907
        },
        {
          "t": 8.5021,
          "s": 0.511351
        },
        {
          "t": 8.566,
          "s": 0.504795
        },
        {
          "t": 8.718,
          "s": 0.498153
        },
        {
          "t": 8.8241,
          "s": 0.491511
        },
        {
          "t": 8.9189,
          "s": 0.484869
        },
        {
          "t": 8.9551,
          "s": 0.478227
        },
        {
          "t": 9.0345,
          "s": 0.471585
        },
        {
          "t": 9.0406,
          "s": 0.464943
        },
        {
          "t": 9.2077,
          "s": 0.458301
        },
        {
          "t": 9.3389,
          "s": 0.451659
        },
        {
          "t": 9.4999,
          "s": 0.445017
        },
        {
          "t": 9.5219,
          "s": 0.438375
        },
        {
          "t": 9.5254,
          "s": 0.431733
        },
        {
          "t": 9.7021,
          "s": 0.425091
        },
        {
          "t": 9.8973,
          "s": 0.418449
        },
        {
          "t": 9.9865,
          "s": 0.411807
        },
        {
          "t": 10.368,
          "s": 0.405165
        },
        {
          "t": 10.5119,
          "s": 0.398523
        },
        {
          "t": 10.6008,
          "s": 0.391881
        },
        {
          "t": 10.6627,
          "s": 0.385238
        },
        {
          "t": 10.7269,
          "s": 0.378596
        },
        {
          "t": 10.8629,
          "s": 0.371954
        },
        {
          "t": 10.9309,
          "s": 0.365312
        },
        {
          "t": 11.0321,
          "s": 0.35867
        },
        {
          "t": 11.1857,
          "s": 0.352028
        },
        {
          "t": 11.3956,
          "s": 0.345386
        },
        {
          "t": 11.414,
          "s": 0.338744
        },
        {
          "t": 11.6331,
          "s": 0.332102
        },
        {
          "t": 11.6376,
          "s": 0.32546
        },
        {
          "t": 11.6667,
          "s": 0.318818
        },
        {
          "t": 11.836,
          "s": 0.312176
        },
        {
          "t": 11.8602,
          "s": 0.305534
        },
        {
          "t": 11.93,
          "s": 0.298892
        },
        {
          "t": 12.0,
          "s": 0.29225
        },
        {
          "t": 12.0,
          "s": 0.285608
        },
        {
          "t": 12.0,
          "s": 0.278966
        },
        {
          "t": 12.0,
          "s": 0.272324
        },
        {
          "t": 12.0,
          "s": 0.265682
        },
        {
          "t": 12.0,
          "s": 0.25904
        },
        {
          "t": 12.0,
          "s": 0.252398
        },
        {
          "t": 12.0,
          "s": 0.245756
        },
        {
          "t": 12.0,
          "s": 0.239114
        },
        {
          "t": 12.0,
          "s": 0.232472
        },
        {
          "t": 12.0,
          "s": 0.225829
        },
        {
          "t": 12.0,
          "s": 0.219187
        },
        {
          "t": 12.0,
          "s": 0.212545
        },
        {
          "t": 12.0,
          "s": 0.205903
        },
        {
          "t": 12.0,
          "s": 0.199261
        },
        {
          "t": 12.0,
          "s": 0.192619
        },
        {
          "t": 12.0,
          "s": 0.185977
        },
        {
          "t": 12.0,
          "s": 0.179335
        },
        {
          "t": 12.0,
          "s": 0.172693
        },
        {
          "t": 12.0,
          "s": 0.166051
        },
        {
          "t": 12.0,
          "s": 0.159409
        },
        {
          "t": 12.0,
          "s": 0.152767
        },
        {
          "t": 12.0,
          "s": 0.146125
        },
        {
          "t": 12.0,
          "s": 0.139483
        },
        {
          "t": 12.0,
          "s": 0.132841
        },
        {
          "t": 12.0,
          "s": 0.126199
        },
        {
          "t": 12.0,
          "s": 0.119557
        },
        {
          "t": 12.0,
          "s": 0.112915
        },
        {
          "t": 12.0,
          "s": 0.106273
        },
        {
          "t": 12.0,
          "s": 0.099631
        },
        {
          "t": 12.0,
          "s": 0.092989
        },
        {
          "t": 12.0,
          "s": 0.086347
        },
        {
          "t": 12.0,
          "s": 0.079705
        },
        {
          "t": 12.0,
          "s": 0.073062
        },
        {
          "t": 12.0,
          "s": 0.06642
        },
        {
          "t": 12.0,
          "s": 0.059778
        },
        {
          "t": 12.0,
          "s": 0.053136
        },
        {
          "t": 12.0,
          "s": 0.046494
        },
        {
          "t": 12.0,
          "s": 0.039852
        },
        {
          "t": 12.0,
          "s": 0.03321
        },
        {
          "t": 12.0,
          "s": 0.026568
        },
        {
          "t": 12.0,
          "s": 0.019926
        },
        {
          "t": 12.0,
          "s": 0.013284
        },
        {
          "t": 12.0,
          "s": 0.006642
        },
        {
          "t": 12.0,
          "s": 0.0
        }
      ]
    },
    {
      "label": "Arm B",
      "coordinates": [
        {
          "t": 0.0,
          "s": 1.0
        },
        {
          "t": 0.179,
          "s": 0.994048
        },
        {
          "t": 0.4672,
          "s": 0.988023
        },
        {
          "t": 0.5054,
          "s": 0.981999
        },
        {
          "t": 0.5207,
          "s": 0.975974
        },
        {
          "t": 0.6387,
          "s": 0.969949
        },
        {
          "t": 0.7373,
          "s": 0.963925
        },
        {
          "t": 0.7418,
          "s": 0.9579
        },
        {
          "t": 0.8459,
          "s": 0.951876
        },
        {
          "t": 0.9689,
          "s": 0.945851
        },
        {
          "t": 1.0643,
          "s": 0.939827
        },
        {
          "t": 1.1802,
          "s": 0.933763
        },
        {
          "t": 1.2799,
          "s": 0.9277
        },
        {
          "t": 1.6367,
          "s": 0.921515
        },
        {
          "t": 1.7785,
          "s": 0.915331
        },
        {
          "t": 1.9115,
          "s": 0.909146
        },
        {
          "t": 1.9312,
          "s": 0.902961
        },
        {
          "t": 1.9347,
          "s": 0.896777
        },
        {
          "t": 1.967,
          "s": 0.890592
        },
        {
          "t": 2.0759,
          "s": 0.884407
        },
        {
          "t": 2.1331,
          "s": 0.878223
        },
        {
          "t": 2.5407,
          "s": 0.871994
        },
        {
          "t": 2.5618,
          "s": 0.865766
        },
        {
          "t": 2.7301,
          "s": 0.859492
        },
        {
          "t": 2.8028,
          "s": 0.853218
        },
        {
          "t": 3.0582,
          "s": 0.846898
        },
        {
          "t": 3.072,
          "s": 0.840578
        },
        {
          "t": 3.1445,
          "s": 0.834258
        },
        {
          "t": 3.1466,
          "s": 0.827938
        },
        {
          "t": 3.1918,
          "s": 0.821618
        },
        {
          "t": 3.4626,
          "s": 0.815249
        },
        {
          "t": 3.5063,
          "s": 0.808778
        },
        {
          "t": 3.5219,
          "s": 0.802308
        },
        {
          "t": 3.6986,
          "s": 0.795838
        },
        {
          "t": 3.7947,
          "s": 0.789368
        },
        {
          "t": 3.9324,
          "s": 0.782897
        },
        {
          "t": 4.1418,
          "s": 0.776427
        },
        {
          "t": 4.1956,
          "s": 0.769957
        },
        {
          "t": 4.3513,
          "s": 0.763432
        },
        {
          "t": 4.4669,
          "s": 0.756907
        },
        {
          "t": 4.4936,
          "s": 0.750382
        },
        {
          "t": 4.7213,
          "s": 0.743741
        },
        {
          "t": 4.9083,
          "s": 0.737041
        },
        {
          "t": 4.9093,
          "s": 0.73034
        },
        {
          "t": 5.2644,
          "s": 0.723515
        },
        {
          "t": 5.3282,
          "s": 0.716689
        },
        {
          "t": 5.4196,
          "s": 0.709864
        },
        {
          "t": 5.4831,
          "s": 0.703038
        },
        {
          "t": 5.8345,
          "s": 0.696008
        },
        {
          "t": 5.9575,
          "s": 0.688977
        },
        {
          "t": 5.9901,
          "s": 0.681947
        },
        {
          "t": 6.1342,
          "s": 0.674843
        },
        {
          "t": 6.3065,
          "s": 0.667664
        },
        {
          "t": 6.3221,
          "s": 0.660485
        },
        {
          "t": 6.4203,
          "s": 0.653306
        },
        {
          "t": 6.507,
          "s": 0.646127
        },
        {
          "t": 6.5819,
          "s": 0.638867
        },
        {
          "t": 6.6139,
          "s": 0.631607
        },
        {
          "t": 6.6219,
          "s": 0.624347
        },
        {
          "t": 6.7132,
          "s": 0.617087
        },
        {
          "t": 6.7615,
          "s": 0.609827
        },
        {
          "t": 6.7879,
          "s": 0.602567
        },
        {
          "t": 6.7921,
          "s": 0.595308
        },
        {
          "t": 6.8852,
          "s": 0.588048
        },
        {
          "t": 6.9108,
          "s": 0.580788
        },
        {
          "t": 6.9145,
          "s": 0.573528
        },
        {
          "t": 6.9328,
          "s": 0.566268
        },
        {
          "t": 7.0185,
          "s": 0.559008
        },
        {
          "t": 7.0842,
          "s": 0.551748
        },
        {
          "t": 7.1304,
          "s": 0.544489
        },
        {
          "t": 7.1551,
          "s": 0.537229
        },
        {
          "t": 7.2123,
          "s": 0.529969
        },
        {
          "t": 7.3081,
          "s": 0.522709
        },
        {
          "t": 7.3169,
          "s": 0.515449
        },
        {
          "t": 7.4005,
          "s": 0.508189
        },
        {
          "t": 7.6043,
          "s": 0.50093
        },
        {
          "t": 7.6379,
          "s": 0.49367
        },
        {
          "t": 7.6962,
          "s": 0.48641
        },
        {
          "t": 7.8614,
          "s": 0.47915
        },
        {
          "t": 8.1544,
          "s": 0.47189
        },
        {
          "t": 8.2772,
          "s": 0.46463
        },
        {
          "t": 8.3049,
          "s": 0.45737
        },
        {
          "t": 8.3567,
          "s": 0.450111
        },
        {
          "t": 8.371,
          "s": 0.442851
        },
        {
          "t": 8.4007,
          "s": 0.435591
        },
        {
          "t": 8.9536,
          "s": 0.427949
        },
        {
          "t": 9.0862,
          "s": 0.420168
        },
        {
          "t": 9.1176,
          "s": 0.412387
        },
        {
          "t": 9.1915,
          "s": 0.404606
        },
        {
          "t": 9.2617,
          "s": 0.396825
        },
        {
          "t": 9.3761,
          "s": 0.389045
        },
        {
          "t": 9.4672,
          "s": 0.381264
        },
        {
          "t": 9.5091,
          "s": 0.373483
        },
        {
          "t": 9.5311,
          "s": 0.365702
        },
        {
          "t": 9.6565,
          "s": 0.357921
        },
        {
          "t": 9.6609,
          "s": 0.35014
        },
        {
          "t": 9.698,
          "s": 0.342359
        },
        {
          "t": 9.8608,
          "s": 0.334397
        },
        {
          "t": 9.8872,
          "s": 0.326435
        },
        {
          "t": 9.9547,
          "s": 0.318474
        },
        {
          "t": 10.1512,
          "s": 0.310512
        },
        {
          "t": 10.5113,
          "s": 0.30255
        },
        {
          "t": 10.6097,
          "s": 0.294588
        },
        {
          "t": 10.6538,
          "s": 0.286405
        },
        {
          "t": 10.8627,
          "s": 0.278222
        },
        {
          "t": 10.8834,
          "s": 0.270039
        },
        {
          "t": 11.4782,
          "s": 0.261856
        },
        {
          "t": 11.7604,
          "s": 0.253673
        },
        {
          "t": 12.0,
          "s": 0.24549
        },
        {
          "t": 12.0,
          "s": 0.237307
        },
        {
          "t": 12.0,
          "s": 0.229124
        },
        {
          "t": 12.0,
          "s": 0.220941
        },
        {
          "t": 12.0,
          "s": 0.212758
        },
        {
          "t": 12.0,
          "s": 0.204575
        },
        {
          "t": 12.0,
          "s": 0.196392
        },
        {
          "t": 12.0,
          "s": 0.188209
        },
        {
          "t": 12.0,
          "s": 0.180026
        },
        {
          "t": 12.0,
          "s": 0.171843
        },
        {
          "t": 12.0,
          "s": 0.16366
        },
        {
          "t": 12.0,
          "s": 0.155477
        },
        {
          "t": 12.0,
          "s": 0.147294
        },
        {
          "t": 12.0,
          "s": 0.139111
        },
        {
          "t": 12.0,
          "s": 0.130928
        },
        {
          "t": 12.0,
          "s": 0.122745
        },
        {
          "t": 12.0,
          "s": 0.114562
        },
        {
          "t": 12.0,
          "s": 0.106379
        },
        {
          "t": 12.0,
          "s": 0.098196
        },
        {
          "t": 12.0,
          "s": 0.090013
        },
        {
          "t": 12.0,
          "s": 0.08183
        },
        {
          "t": 12.0,
          "s": 0.073647
        },
        {
          "t": 12.0,
          "s": 0.065464
        },
        {
          "t": 12.0,
          "s": 0.057281
        },
        {
          "t": 12.0,
          "s": 0.049098
        },
        {
          "t": 12.0,
          "s": 0.040915
        },
        {
          "t": 12.0,
          "s": 0.032732
        },
        {
          "t": 12.0,
          "s": 0.021821
        },
        {
          "t": 12.0,
          "s": 0.010911
        },
        {
          "t": 12.0,
          "s": 0.0
        }
      ]
    }
  ],
  "axis": {
    "x_min": 0,
    "x_max": 12
  }
}